MANIFEST.in
setup.cfg
setup.py
tenyks/__init__.py
tenyks/banner.py
tenyks/commandmapping.py
tenyks/commands.py
tenyks/config.py
tenyks/connection.py
tenyks/constants.py
tenyks/core.py
tenyks/exceptions.py
tenyks/logs.py
tenyks/middleware.py
tenyks/module_loader.py
tenyks/settings.py.dist
tenyks/termcolors.py
tenyks/utils.py
tenyks.egg-info/PKG-INFO
tenyks.egg-info/SOURCES.txt
tenyks.egg-info/dependency_links.txt
tenyks.egg-info/entry_points.txt
tenyks.egg-info/not-zip-safe
tenyks.egg-info/requires.txt
tenyks.egg-info/top_level.txt
tenyks/client/__init__.py
tenyks/client/client.py
tenyks/client/config.py
tenyks/client/models.py