Metadata-Version: 1.0
Name: tenyks
Version: 0.2.1
Summary: Redis powered IRC bot
Home-page: https://github.com/kyleterry/tenyks
Author: Kyle Terry
Author-email: kyle@kyleterry.com
License: LICENSE
Keywords: irc bot redis
Platform: UNKNOWN
